<BloggerCollection>
	<Blogger Name="C&eacute;sar L&oacute;pez Natar&eacute;n" RssUrl="http://cesarnataren.blogspot.com/feeds/posts/default?alt=rss" IrcNick="cesar" Head="cesar.png"/>
	<Blogger Name="Miguel de Icaza" RssUrl="http://tirania.org/blog/miguel.rss2" IrcNick="miguel"/>
	<Blogger Name="Jackson Harper" RssUrl="http://feeds.feedburner.com/JacksonsActivityLog" IrcNick="jackson" />
	<Blogger Name="Sebastien Pouliot" RssUrl="http://pages.infinit.net/ctech/poupou.rss" IrcNick="spouliot" Head="Spouliot.png"/>
	<Blogger Name="Mike Kestner" RssUrl="http://mkestner.blogspot.com/feeds/posts/default?alt=rss" IrcNick="mkestner"/>
	<Blogger Name="Lluis Sanchez " RssUrl="http://foodformonkeys.blogspot.com/feeds/posts/default?alt=rss" IrcNick="lluis" Head="Lluis.png"/>
	<Blogger Name="Duncan Mak " RssUrl="http://www.a-chinaman.com/category/monologue/feed" IrcNick="duncan" Head="Duncan.png"/>
	<Blogger Name="Martin Baulig" RssUrl="http://primates.ximian.com/~martin/blog/martin.rss2" IrcNick="baulig" Head="Martin.png" />
	<Blogger Name="Martin Willemoes Hansen" RssUrl="http://mwhansen.blogspot.com/rss.xml" Head="Mwh.png" />
	<Blogger Name="Todd Berman" RssUrl="http://off.net/~tberman/diary/index.xml" IrcNick="tberman" Head="Tberman.png" />
	<Blogger Name="Mono" RssUrl="http://www.mono-project.com/news/index.rss2" Head="mono.png" />
	<Blogger Name="Gonzalo Paniagua Javier" RssUrl="http://gonzalo.name/blog/gonzalo.rss2" IrcNick="gonzalo" Head="gonzalo.png"/>
	<Blogger Name="Daniel Morgan" RssUrl="http://www.mfconsulting.com/danmorg/blog/monologue-index.xml" IrcNick="danmorg"/>
	<Blogger Name="Atsushi Enomoto" RssUrl="http://veritas-vos-liberabit.com/lb/index.rss2" IrcNick="eno"/>
	<Blogger Name="Paolo Molaro" RssUrl="http://www.advogato.org/person/lupus/rss.xml"/>
	<Blogger Name="Larry Ewing" RssUrl="http://primates.ximian.com/~lewing/blog/index.rdf" IrcNick="lewing" Head="lewing.png"/>
	<Blogger Name="John Luke" RssUrl="http://spaces.msn.com/members/jluke19/feed.rss" IrcNick="jluke"/>
	<Blogger Name="Vladimir Vukicevic" RssUrl="http://blog.vlad1.com/feed/" IrcNick="vlad"/>
	<!-- by popular demand 
	<Blogger Name="Edd Dumbill" RssUrl="http://usefulinc.com/edd/blog/rss91" Head="edd.png" IrcNick="edd" />
	-->
	<Blogger Name="Massimiliano Mantione" RssUrl="http://primates.ximian.com/~massi/blog/index.rdf" Head="massi-hackergotchi.png" IrcNick="massi" />
	<Blogger Name="Nemerle" RssUrl="http://nemerle.org/blog/nemerle.rss2" Head="nemerle.png" />
	<Blogger Name="Jon Trowbridge" RssUrl="http://blog.trowbridge.org/wp-rss2.php" IrcNick="trow" Head="trow.png"/>
	<Blogger Name="Paco Martinez" RssUrl="http://www.mfconsulting.com/blog/index.rdf" IrcNick="paco" Head="paco.png"/>        
	<Blogger Name="Jambunathan K" RssUrl="http://feeds.feedburner.com/DiaryOfAVBDotNetCompilerDeveloper"/>        
	<Blogger Name="Umadevi S" RssUrl="http://www.gnomebangalore.org/?q=blog/feed/599"/>        
	<Blogger Name="Sureshkumar" RssUrl="http://www.gnomebangalore.org/?q=blog/feed/677" IrcNick="suresh"/>
	<Blogger Name="Geoff Norton" RssUrl="http://blog.sublimeintervention.com/kangaroo.rss2" IrcNick="kangaroo" />
	<Blogger Name="Alex Graveley" RssUrl="http://www.beatniksoftware.com/blog/wp-rss2.php" IrcNick="orph" Head="orph.png"/>
	<Blogger Name="Chris Toshok" RssUrl="http://squeedlyspooch.com/blog/geek-index.xml" IrcNick="toshok" Head="toshok.png" />
	<!--Blogger Name="Joseph Hill" RssUrl="http://www.beyondfocus.com/WeblogX/BlogXBrowsing.asmx/GetRss?" IrcNick="jhill" Head="jhill.png"/-->
	<Blogger Name="Jb Evain" RssUrl="http://evain.net/ruby/userland.rbx" IrcNick="jbevain" Head="jbevain.png" />
	<Blogger Name="Zac Bowling" RssUrl="http://zacbowling.com/blog/category/mono-net/feed/rss2" IrcNick="zbowling" />
	<Blogger Name="Mark Crichton" RssUrl="http://www.fishysnax.com/category/code/feed/rss2" IrcNick="mmarker" Head="crichtma.png" />
	<!-- no longer maintained and Novell no longer owns this domain
	<Blogger Name="MWF Weblog" RssUrl="http://svn.myrealbox.com/blog/rss.xml"/>
	 -->
	<Blogger Name="Christian Hergert" RssUrl="http://www.vwdude.com/xml/mono/feed.xml" IrcNick="vwdude" Head="vwdude.png" />
  <Blogger Name  ="Monocast"
           RssUrl="http://mono-cast.com/?feed=rss2&amp;category_name=mono"
           Head  ="monocast.png"
           />
  <Blogger Name   ="C.J. Adams-Collier"
           RssUrl ="http://wp.colliertech.org/cj/?feed=rss2&amp;cat=7"
           IrcNick="cj"
           Head   ="cj.png"
           />
  <Blogger Name   ="Rafael Ferreira"
           RssUrl ="http://ophion.org/data/xml/blog.rss"
           IrcNick="raf"
	   />
	<Blogger Name="Jeroen Frijters" RssUrl="http://weblog.ikvm.net/SyndicationService.asmx/GetRss" IrcNick="jeroen"/>
	<Blogger Name="Eric Butler" RssUrl="http://eric.extremeboredom.net/rss.xml" IrcNick="FireRabbit"/>
	<Blogger Name="Joe Audette" RssUrl="http://www.joeaudette.com/aggregator283rss.aspx"/>
	<Blogger Name="Michael Giagnocavo" RssUrl="http://www.atrevido.net/blog/SyndicationService.asmx/GetRss"/>
	<Blogger Name="Dan Winship" RssUrl="http://mysterion.org/~danw/blog/index.rss" IrcNick="danw" Head="danw.png" />
	<Blogger Name="Carlos Alberto Cortez" RssUrl="http://feeds.feedburner.com/carlos"/>
	<Blogger Name="Joshua Tauberer" RssUrl="http://razor.occams.info/blog/category/mono/feed"/>
	<Blogger Name="Peter Johanson" RssUrl="http://www.tenslashsix.com/wp-feed.php?cat=5" IrcNick="latexer" Head="latexer.png"/>
	<Blogger Name="Aaron Bockover" RssUrl="http://abock.org/feed" IrcNick="abock" Head="abock.png"/>
	<Blogger Name="Rafi Mizrahi" RssUrl="http://feeds.feedburner.com/RafaelMizrahisWebLog" Head="rafi_mizrahi_head.png"/>
	<Blogger Name="Michael Dominik" RssUrl="http://www.mdk.org.pl/xml/rss20/feed.xml" IrcNick="mdk" Head="mdk_gotchi.png" />
	<Blogger Name="Mario Sopena" RssUrl="http://feeds.feedburner.com/marioRss" IrcNick="mario"/>
	<Blogger Name="Pedro Martinez" RssUrl="http://pedromj.dyndns.org/blog/BlogXBrowsing.asmx/GetRss?" Head="Pedro.png"/>
	<!--<Blogger Name="Brandon Hale" RssUrl="http://blog.brandonhale.us/xml/rss20/feed.xml" IrcNick="bhale"/>-->
	<Blogger Name="Raja R Harinath" RssUrl="http://feeds.feedburner.com/hurrynot" Head="Harinath.jpg"/>
	<Blogger Name="Mirco Bauer" RssUrl="http://www.meebey.net/jaws/data/xml/blog.Mono.rss" />
	<Blogger Name="Michael Hutchinson" RssUrl="http://compsoc.dur.ac.uk/~mjh/mono-feed"/>
	<Blogger Name="Jeff Tickle" RssUrl="http://blog.jefftickle.com/category/pub/rss2" IrcNick="jtickle" Head="jtickle.png" />
	<Blogger Name="Marek Sieradzki" RssUrl="http://msieradzki.wordpress.com/feed/" IrcNick="msieradzki" />
	<Blogger Name="Ben Maurer" RssUrl="http://feeds.feedburner.com/bmaurer" IrcNick="BenM" Head="benm-face.png"/>
	<Blogger Name="Ritvik Mayank" RssUrl="http://feeds.feedburner.com/mritvik" />
	<Blogger Name="Boris Kirzner" RssUrl="http://boriskirzner.wordpress.com/feed" IrcNick="borisk" Head="borisk.png"/>
	<Blogger Name="James Wilcox" RssUrl="http://www.snorp.net/log/?feed=rss2" IrcNick="snorp" Head="snorp.png" />
	<Blogger Name="Brad Taylor" RssUrl="http://brad.getcoded.net/blog/rss.php" IrcNick="brad" Head="brad.png" /> 
	<Blogger Name="Rodrigo B de Oliveira" RssUrl="http://feeds.feedburner.com/Bamboozled" IrcNick="bamboo"/>
	<!-- Removed: returning 404 for quite a while now.
	<Blogger Name="Raphael Romeikat" RssUrl="http://blog.raffa.de/rss.php?ver=2" Head="raphaphp.png"/>
	-->
	<Blogger Name="Rafael Teixeira" RssUrl="http://monoblog.blogspot.com/feeds/posts/default?alt=rss" IrcNick="monoman" Head="monoman.png"/> 
	<Blogger Name="Alexandre Gomes" RssUrl="http://www.alexandre-gomes.com/?feed=rss2&amp;cat=19" IrcNick="Alexmipego"/>
	<Blogger Name="Jonathan Chambers" RssUrl="http://jonathanchambers.blogspot.com/feeds/posts/default?alt=rss" IrcNick="jchambers"/>
	<Blogger Name="Jonathan Pryor" RssUrl="http://www.jprl.com/Blog/jon.rss2" IrcNick="jonp" Head="jonpryor.png"/>
	<Blogger Name="Jordi Mas" RssUrl="http://www.softcatala.org/~jmas/weblog/rss.xml" IrcNick="Jordi" Head="Jordi.png"/>	
	<Blogger Name="Idan Gazit" RssUrl="http://pixane.net/blog/?feed=rss2&amp;cat=2" IrcNick="idan" Head="Idan.png"/>
	<Blogger Name="Ankit Jain" RssUrl="http://ankitjain.org/blog/?feed=rss2&amp;cat=2" IrcNick="ankit"/>
	<Blogger Name="Wade Berrier" RssUrl="http://wadeberrier.blogspot.com/feeds/posts/default?alt=rss" IrcNick="wberrier"/>
	<Blogger Name="Maurits Rijk" RssUrl="http://maurits.wordpress.com/feed/" />
	<Blogger Name="Michael Zucchi" RssUrl="http://www.users.on.net/~notzed/notzed.rdf" IrcNick="NotZed"/>
	<Blogger Name="Kenneth Christiansen" RssUrl="http://feeds.feedburner.com/CodePosts"/>
	<Blogger Name="Gabriel Burt" RssUrl="http://feeds.feedburner.com/blogspot/lWNb" IrcNick="gabaug" Head="gabaug.png" />
	<Blogger Name="Joe Shaw" RssUrl="http://joeshaw.org/feed/" IrcNick="joe" Head="joe.png" />
	<Blogger Name="Alan McGovern" RssUrl="http://feeds.feedburner.com/MonoTorrent" IrcNick="_Alan_"/>
	<Blogger Name="Boyd Timothy" RssUrl="http://blog.timothy.ws/rss.xml" IrcNick="boyd" Head="boyd.png" />
	<Blogger Name="Patrick van Staveren" RssUrl="http://trick.vanstaveren.us/wp/feed/" IrcNick="trick" />
	<Blogger Name="Andreia Gaita" RssUrl="http://worldofcoding.blogspot.com/feeds/posts/default?alt=rss" IrcNick="shana" />
	<Blogger Name="Antti Juhani Oja" RssUrl="http://sandriman.wordpress.com/feed/" IrcNick="Sandriman"/>
	<Blogger Name="Nagappan Alagappan" RssUrl="http://nagappanal.blogspot.com/rss.xml" IrcNick="nags"/>
	<Blogger Name="Everaldo Canuto" RssUrl="http://ecanuto.blogspot.com/feeds/posts/default/-/mono?alt=rss" IrcNick="everaldo"/>
	<Blogger Name="Jonathan Pobst" RssUrl="http://jpobst.blogspot.com/feeds/posts/default?alt=rss" IrcNick="jpobst"/>
	<Blogger Name="Rolf Bjarne Kvinge" RssUrl="http://rolfkvinge.blogspot.com/feeds/posts/default?alt=rss" IrcNick="rolf"/>
	<Blogger Name="Marek Safar" RssUrl="http://mareksafar.blogspot.com/feeds/posts/default?alt=rss" IrcNick="Marek"/>
	<Blogger Name="Wbem Tools" RssUrl="http://wbemtools.blogspot.com/feeds/posts/default?alt=rss" Head="WbemTools.png"/>
	<Blogger Name="Marek Habersack" RssUrl="http://grendello.blogspot.com/feeds/posts/default?alt=rss" IrcNick="grendel" />
	<Blogger Name="Jeffrey Stedfast" RssUrl="http://jeffreystedfast.blogspot.com/feeds/posts/default?alt=rss" IrcNick="fejj"/>
	<Blogger Name="Codice Software" RssUrl="http://codicesoftware.blogspot.com/feeds/posts/default?alt=rss"/>
	<Blogger Name="Jamie Cansdale" RssUrl="http://weblogs.asp.net/nunitaddin/rss.aspx?Tags=Mono&amp;AndTags=1"/>
	<Blogger Name="Albert Gnandt"
	RssUrl="http://gnandt.blogspot.com/feeds/posts/default/-/Monologue?alt=rss"/>
        <Blogger Name="Scott Peterson" RssUrl="http://www.themonkeysgrinder.blogspot.com/feeds/posts/default?alt=rss"/>
	<Blogger Name="Ivan N. Zlatev" RssUrl="http://i-nz.net/category/software-development/mono/feed" IrcNick="i-nz"/>
	<Blogger Name="Brian Nickel" RssUrl="http://kerrick.wordpress.com/tag/summer-of-code-2007/feed/"/>
	<Blogger Name="Gernot Margreitner" RssUrl="http://gernot.wordpress.com/tag/mono-image-processing/feed/"/>
	<Blogger Name="Hector Gomez"
	RssUrl="http://hectoregm.blogspot.com/feeds/posts/default?alt=rss"/>
	<Blogger Name="Ben Motmans"
	RssUrl="http://bmotmans.blogspot.com/feeds/posts/default?alt=rss" IrcNick="tremor"/>
	<Blogger Name="Nestor Salceda"
	RssUrl="http://nestor.babuine.net/?cat=8&amp;feed=rss2"/>
	<Blogger Name="Marcos Cobena" RssUrl="http://www.youcannoteatbits.org/Blog/SoC.xml" IrcNick="m4rc05" /> 
	<Blogger Name="Matej Spiller" RssUrl="http://matejsp.blogspot.com/feeds/posts/default?alt=rss"/>
	<Blogger Name="Marcos Marin" RssUrl="http://mdmagsoc.blogspot.com/feeds/posts/default?alt=rss"/>
	<Blogger Name="Leonardo Pires" RssUrl="http://aspnetajax.blogspot.com/feeds/posts/default?alt=rss"/>
	<Blogger Name="Kenny Parnell" RssUrl="http://feeds.feedburner.com/soc2007" IrcNick="kennyp"/>
	<Blogger Name="Khaled" RssUrl="http://madinatek.blogspot.com/feeds/posts/default?alt=rss" />
	<Blogger Name="Debackerl" RssUrl="http://debackerl.wordpress.com/tag/soc-2007/feed/" />
	<Blogger Name="Nidhi Rawal" RssUrl="http://nidhi24.wordpress.com/?feed=rss" />
	<Blogger Name="Jared Hendry" RssUrl="http://buchan.esoteriq.org/weblog/category/mono/feed" />
	<Blogger Name="Chris Howie" RssUrl="http://www.chrishowie.com/feed/" IrcNick="SerajewelKS" Head="chrishowie.png"/>
	<Blogger Name="David Srbecky" RssUrl="http://community.sharpdevelop.net/blogs/dsrbecky/rss.aspx?Tags=Mono"/>
	<Blogger Name="Chris Gameweld" RssUrl="http://gameweld-soc.blogspot.com/feeds/posts/default?alt=rss" />
	<Blogger Name="Joel Reed" RssUrl="http://ropeonfire.blogspot.com/feeds/posts/default?alt=rss" />
	<Blogger Name="Valentin Sawadski" RssUrl="http://achblah.blogspot.com/feeds/posts/default?alt=rss" />
	<Blogger Name="Seo Sanghyeon" RssUrl="http://fepy.blogspot.com/feeds/posts/default?alt=rss" IrcNick="sanxiyn"/>
	<Blogger Name="Alp Toker" RssUrl="http://www.atoker.com/blog/feed" IrcNick="alp"/>
	<Blogger Name="Mark Probst" RssUrl="http://schani.wordpress.com/feed/" IrcNick="schani"/>
	<Blogger Name="Will Johansson" RssUrl="http://mwfosx.blogspot.com/feeds/posts/default?alt=rss"/>
	<Blogger Name="Mainsoft Grasshopper" RssUrl="http://feeds.feedburner.com/grasshopper"/>
	<Blogger Name="Francisco Figueiredo" RssUrl="http://fxjr.blogspot.com/feeds/posts/default?alt=rss"/>
	<Blogger Name="R. Tyler Ballance" RssUrl="http://www.unethicalblogger.com/blog_categories/mono/feed" IrcNick="rtyler"/>
	<Blogger Name="Olivier Dufour" RssUrl="http://dufoli.wordpress.com/feed/"/>
	<Blogger Name="Andrew Jorgensen" RssUrl="http://andrew.jorgensenfamily.us/feed/" Head="ajorg.png" IrcNick="ajorgensen"/>	
</BloggerCollection>
